opsys_integrating_sphere/__init__.py
opsys_integrating_sphere/artifex_controller.py
opsys_integrating_sphere/i_sphere_abstract.py
opsys_integrating_sphere/i_sphere_controller.py
opsys_integrating_sphere/ophir_controller.py
opsys_integrating_sphere-0.0.6.dist-info/LICENSE
opsys_integrating_sphere-0.0.6.dist-info/METADATA
opsys_integrating_sphere-0.0.6.dist-info/WHEEL
opsys_integrating_sphere-0.0.6.dist-info/top_level.txt
opsys_integrating_sphere-0.0.6.dist-info/RECORD
